Workbook

Sheet CVM
A1: Data_Posicao | B1: ID_CNPJ_Fundo | C1: Nome_Fundo | D1: Fonte | E1: Tem na Raspagem
A2: 46171 | B2: 05754060000113 | C2: CATERPILLAR FUNDO DE INVESTIMENTO EM DIREITOS CREDITÓRIOS DO SEGMENTO INDUSTRIAL II - RESP LIMITADA | D2: CVM | E2: =_xlfn.XLOOKUP(B2,RASPAGEM_REGULAMENTOS!A:A,RASPAGEM_REGULAMENTOS!C:C) -> Raspagem
A3: 46171 | B3: 06018364000185 | C3: FUNDO DE INVESTIMENTO EM DIREITOS CREDITÓRIOS - FIDC PREMIUM | D3: CVM | E3: =_xlfn.XLOOKUP(B3,RASPAGEM_REGULAMENTOS!A:A,RASPAGEM_REGULAMENTOS!C:C) -> Raspagem
A4: 46171 | B4: 06081379000198 | C4: KOL FUNDO DE INVESTIMENTO EM DIREITOS CREDITÓRIOS NÃO-PADRONIZADOS | D4: CVM | E4: =_xlfn.XLOOKUP(B4,RASPAGEM_REGULAMENTOS!A:A,RASPAGEM_REGULAMENTOS!C:C) -> Raspagem
A5: 46171 | B5: 06182371000118 | C5: FOR-TE FIDC | D5: CVM | E5: =_xlfn.XLOOKUP(B5,RASPAGEM_REGULAMENTOS!A:A,RASPAGEM_REGULAMENTOS!C:C) -> Raspagem
A6: 46171 | B6: 07084253000130 | C6: MULTI INFRA FUNDO DE INVESTIMENTO EM DIREITOS CREDITÓRIOS NÃO-PADRONIZADOS | D6: CVM | E6: =_xlfn.XLOOKUP(B6,RASPAGEM_REGULAMENTOS!A:A,RASPAGEM_REGULAMENTOS!C:C) -> Raspagem
A7: 46171 | B7: 07383363000100 | C7: RIVO FUNDO DE INVESTIMENTO EM DIREITOS CREDITÓRIOS | D7: CVM | E7: =_xlfn.XLOOKUP(B7,RASPAGEM_REGULAMENTOS!A:A,RASPAGEM_REGULAMENTOS!C:C) -> Raspagem
A8: 46171 | B8: 07507899000182 | C8: GP FIDC FCVS | D8: CVM | E8: =_xlfn.XLOOKUP(B8,RASPAGEM_REGULAMENTOS!A:A,RASPAGEM_REGULAMENTOS!C:C) -> Raspagem
A9: 46171 | B9: 07727002000126 | C9: FIDC PCG - BRASIL MULTICARTEIRA | D9: CVM | E9: =_xlfn.XLOOKUP(B9,RASPAGEM_REGULAMENTOS!A:A,RASPAGEM_REGULAMENTOS!C:C) -> Raspagem
A10: 46171 | B10: 07727757000120 | C10: EMPRESARIAL FUNDO DE INVESTIMENTO EM DIREITOS CREDITÓRIOS MULTISEGMENTOS | D10: CVM | E10: =_xlfn.XLOOKUP(B10,RASPAGEM_REGULAMENTOS!A:A,RASPAGEM_REGULAMENTOS!C:C) -> Raspagem
A11: 46171 | B11: 07738319000168 | C11: SP RECEBÍVEIS PREMIUM I FUNDO DE INVESTIMENTO EM DIREITOS CREDITÓRIOS MULTISSEGMENTOS | D11: CVM | E11: =_xlfn.XLOOKUP(B11,RASPAGEM_REGULAMENTOS!A:A,RASPAGEM_REGULAMENTOS!C:C) -> Raspagem
A12: 46171 | B12: 07742454000187 | C12: GP - FIDC FCVS 2 | D12: CVM | E12: =_xlfn.XLOOKUP(B12,RASPAGEM_REGULAMENTOS!A:A,RASPAGEM_REGULAMENTOS!C:C) -> Raspagem
A13: 46171 | B13: 08093745000154 | C13: V1 FUNDO DE INVESTIMENTO EM DIREITOS CREDITÓRIOS - MULTICARTEIRA | D13: CVM | E13: =_xlfn.XLOOKUP(B13,RASPAGEM_REGULAMENTOS!A:A,RASPAGEM_REGULAMENTOS!C:C) -> Raspagem
... A4222: 46171 | B4222: 97533979000103 | C4222: FUNDO DE INVESTIMENTO EM DIREITOS CREDITORIOS CASH FLOW MULTISSEGMENTOS | D4222: CVM | E4222: =_xlfn.XLOOKUP(B4222,RASPAGEM_REGULAMENTOS!A:A,RASPAGEM_REGULAMENTOS!C:C) -> Raspagem

Sheet RASPAGEM_REGULAMENTOS
A1: cnpj_tratado | B1: nome_fundo | C1: Fonte
A2: 09009924000123 | B2: Eco – Multi Commodities Fundo de Investimento em Direitos Creditórios Agropecuários | C2: Raspagem
A3: 17198822000121 | B3: ROVENSA FUNDO DE INVESTIMENTO EM DIREITOS CREDITÓRIOS AGRONEGÓCIO RESPONSABILIDADE LIMITADA | C3: Raspagem
A4: 18686800000173 | B4: CERRADO I FUNDO DE INVESTIMENTO EM DIREITOS CREDITÓRIOS | C4: Raspagem
A5: 20998706000100 | B5: FMC 202201 FUNDO DE INVESTIMENTO EM DIREITOS CREDITÓRIOS – RESPONSABILIDADE LIMITADA | C5: Raspagem
A6: 24270541000106 | B6: DISAM CASH - FUNDO DE INVESTIMENTO EM DIREITOS CREDITÓRIOS DO AGRONEGÓCIO DE RESPONSABILIDADE ILIMITADA | C6: Raspagem
A7: 25382606000160 | B7: URA AGRO FUNDO DE INVESTIMENTO EM DIREITOS CREDITÓRIOS – RESPONSABILIDADE LIMITADA | C7: Raspagem
A8: 25382606000160 | C8: Raspagem
A9: 26459204000189 | B9: JAPUÍRA FUNDO DE INVESTIMENTO EM DIREITOS CREDITÓRIOS - RESPONSABILIDADE LIMITADA | C9: Raspagem
A10: 28472392000100 | B10: UPL 1 FUNDO DE INVESTIMENTO EM DIREITOS CREDITÓRIOS AGRONEGÓCIO | C10: Raspagem
A11: 31771948000174 | B11: VLA FUNDO DE INVESTIMENTO EM DIREITOS CREDITÓRIOS – RESPONSABILIDADE LIMITADA | C11: Raspagem
A12: 35654776000100 | B12: PANTANAL DO BRASIL FUNDO DE INVESTIMENTO EM DIREITOS CREDITÓRIOS NÃO PADRONIZADOS | C12: Raspagem
A13: 37035910000110 | B13: AG LIFE FUNDO DE INVESTIMENTO EM DIREITOS CREDITÓRIOS | C13: Raspagem
A14: 37036039000179 | B14: GREEN LIFE ESG FUNDO DE INVESTIMENTO EM DIREITOS CREDITÓRIOS | C14: Raspagem
A15: 40365928000194 | B15: FARM II FUNDO DE INVESTIMENTO EM DIREITOS CREDITÓRIOS RESPONSABILIDADE LIMITADA | C15: Raspagem
A16: 40365928000194 | C16: Raspagem
A17: 41196339000192 | B17: SYNGENTA TECH I FUNDO DE INVESTIMENTO EM DIREITOS CREDITÓRIOS DE RESPONSABILIDADE ILIMITADA | C17: Raspagem
A18: 41196339000192 | C18: Raspagem
A19: 41196339000192 | B19: SYNGENTA TECH I FUNDO DE INVESTIMENTO EM DIREITOS CREDITÓRIOS | C19: Raspagem
A20: 42336323000109 | B20: CERES CONFINA FUNDO DE INVESTIMENTO EM DIREITOS CREDITÓRIOS – RESPONSABILIDADE LIMITADA | C20: Raspagem
A21: 43616659000180 | B21: TALÓ 1 FUNDO DE INVESTIMENTO EM DIREITOS CREDITÓRIOS RESPONSABILIDADE LIMITADA | C21: Raspagem
A22: 44302112000172 | B22: FUNDO DE INVESTIMENTO EM DIREITOS CREDITÓRIOS AGRO CITI-BAYER RESPONSABILIDADE LIMITADA | C22: Raspagem
A23: 44613189000163 | B23: BIOMA INVESTIMENTOS FIAGRO EM DIREITOS CREDITÓRIOS | C23: Raspagem
A24: 46073195000109 | B24: FUNDO DE INVESTIMENTO EM DIREITOS CREDITÓRIOS AGRO CITI-SYNGENTA | C24: Raspagem
A25: 46073195000109 | B25: FUNDO DE INVESTIMENTO EM DIREITOS CREDITÓRIOS AGRO CITI-SYNGENTA RESPONSABILIDADE LIMITADA | C25: Raspagem
A26: 46390186000133 | B26: SEED FUNDO DE INVESTIMENTO EM DIREITOS CREDITÓRIOS NÃO PADRONIZADOS | C26: Raspagem
A27: 46390255000109 | B27: CULTURA AGROMAIS FUNDO DE INVESTIMENTO EM DIREITOS CREDITÓRIOS | C27: Raspagem
A28: 46442274000131 | B28: FARM III FUNDO DE INVESTIMENTO EM DIREITOS CREDITÓRIOS RESPONSABILIDADE LIMITADA | C28: Raspagem
A29: 47228232000165 | B29: Classe Única Agro Flex Fundo de Investimento em Direitos Creditórios – Responsabilidade Limitada | C29: Raspagem
A30: 47228232000165 | C30: Raspagem
A31: 47669450000135 | B31: MAKALU FUNDO DE INVESTIMENTO EM DIREITOS CREDITÓRIOS RESPONSABILIDADE LIMITADA | C31: Raspagem
A32: 47936587000109 | B32: FARM M II FUNDO DE INVESTIMENTO EM DIREITOS CREDITÓRIOS RESPONSABILIDADE LIMITADA | C32: Raspagem
A33: 47936587000109 | C33: Raspagem
A34: 48313595000161 | B34: IBBA AGRO BR FUNDO DE INVESTIMENTO EM DIREITOS CREDITÓRIOS | C34: Raspagem
A35: 48660463000106 | B35: FARMTECH UP CREDIT FUNDO DE INVESTIMENTO EM DIREITOS CREDITÓRIOS | C35: Raspagem
A36: 48660463000106 | B36: Fundo de Investimento em Direitos Creditórios | C36: Raspagem
A37: 48890745000108 | B37: G5 FARM FUNDO DE INVESTIMENTO EM COTAS DE FUNDOS DE INVESTIMENTO EM DIREITOS CREDITÓRIOS III | C37: Raspagem
A38: 48935526000190 | B38: CERES CRA FUNDO DE INVESTIMENTO EM DIREITOS CREDITÓRIOS | C38: Raspagem
A39: 50519168000186 | B39: STRUTTURA AGRO FUNDO DE INVESTIMENTO EM DIREITOS CREDITÓRIOS DO AGRONEGÓCIO | C39: Raspagem
A40: 51554551000138 | B40: CRÉDITO NITRO AGRO – RESPONSABILIDADE LIMITADA | C40: Raspagem
A41: 51554551000138 | C41: Raspagem
A42: 51764889000114 | B42: BIGTRADE SUNO FUNDO DE INVESTIMENTO | C42: Raspagem
A43: 52093999000164 | B43: VALORIZA FUNDO DE INVESTIMENTO EM DIREITOS CREDITÓRIOS | C43: Raspagem
A44: 52680835000133 | B44: ATVOS ENERGIA RENOVÁVEL FUNDO DE INVESTIMENTO EM DIREITOS CREDITÓRIOS RESPONSABILIDADE LIMITADA | C44: Raspagem
A45: 52804600000106 | B45: AGRO – OPEN GROWTH SILOS RESPONSABILIDADE LIMITADA | C45: Raspagem
A46: 52804600000106 | B46: AGRO – OPEN GROWTH SILOS | C46: Raspagem
A47: 53042591000126 | B47: TFO FERTAGRO FUNDO DE INVESTIMENTO EM DIREITOS CREDITÓRIOS | C47: Raspagem
A48: 53257790000151 | B48: FARM M III FUNDO DE INVESTIMENTO EM DIREITOS CREDITÓRIOS RESPONSABILIDADE | C48: Raspagem
A49: 53257790000151 | C49: Raspagem
A50: 53273825000146 | B50: Fundo de Investimento em Direitos Creditórios Agro Opea Cocari de Responsabilidade Limitada | C50: Raspagem
A51: 54114034000136 | B51: BRAVANO FUNDO DE INVESTIMENTO EM DIREITOS CREDITÓRIOS | C51: Raspagem
A52: 54427293000117 | B52: FOCO CAPITAL FIAGRO EM DIREITOS CREDITÓRIOS RESPONSABILIDADE LIMITADA | C52: Raspagem
A53: 54619490000138 | B53: SAFRAS AGRO FUNDO DE INVESTIMENTO EM DIREITOS CREDITÓRIOS | C53: Raspagem
A54: 54773936000184 | B54: TALÓ II FUNDO DE INVESTIMENTO EM DIREITOS CREDITÓRIOS | C54: Raspagem
A55: 54857414000160 | B55: INDIE MERX RAIZ I CRÉDITO AGRO FUNDO DE INVESTIMENTO EM DIREITOS CREDITÓRIOS DO AGRONEGÓCIO | C55: Raspagem
A56: 54857414000160 | C56: Raspagem
A57: 55102997000182 | B57: ARC FUNDO DE INVESTIMENTO NAS CADEIAS PRODUTIVAS DO AGRONEGÓCIO – DIREITOS CREDITÓRIOS – RESPONSABILIDADE LIMITADA | C57: Raspagem
A58: 55102997000182 | C58: Raspagem
A59: 55144736000125 | B59: RENOVAGRO FUNDO DE INVESTIMENTO EM DIREITOS CREDITÓRIOS | C59: Raspagem
A60: 55691548000117 | B60: LIQ FUNDO DE INVESTIMENTO NAS CADEIAS PRODUTIVAS AGROINDUSTRIAIS – FIAGRO – DIREITOS CREDITÓRIOS | C60: Raspagem
A61: 57053395000108 | B61: AGROCANA FUNDO DE INVESTIMENTO EM DIREITOS CREDITÓRIOS – RESPONSABILIDADE LIMITADA | C61: Raspagem
A62: 57074057000152 | B62: MOVE BRASIL FUNDO DE INVESTIMENTO EM DIREITOS CREDITÓRIOS DO AGRONEGÓCIO | C62: Raspagem
A63: 57325251000163 | B63: ANGICO FUNDO DE INVESTIMENTO EM DIREITOS CREDITÓRIOS SEGMENTO INFRAESTRUTURA E AGRONEGÓCIO DE RESPONSABILIDADE LIMITADA | C63: Raspagem
A64: 57532782000127 | B64: COFFEE BANK FUNDO DE INVESTIMENTO EM DIREITOS CREDITÓRIOS FINANCEIROS DO AGRONEGÓCIO DE RESPONSABILIDADE LIMITADA | C64: Raspagem
A65: 58033643000111 | B65: RIO BRAVO AGRO RECEBÍVEIS FUNDO DE INVESTIMENTO EM DIREITOS CREDITÓRIOS DE RESPONSABILIDADE LIMITADA | C65: Raspagem
A66: 58033772000100 | B66: BELAGRÍCOLA FUNDO DE INVESTIMENTO EM DIREITOS CREDITÓRIOS | C66: Raspagem
A67: 58442833000192 | B67: FARM M IV FUNDO DE INVESTIMENTO EM DIREITOS CREDITÓRIOS RESPONSABILIDADE LIMITADA | C67: Raspagem
A68: 58442833000192 | B68: DIREITOS CREDITÓRIOS RESPONSABILIDADE LIMITADA | C68: Raspagem
A69: 59524577000145 | B69: FUNDO DE INVESTIMENTO EM DIREITOS CREDITÓRIOS - DAV | C69: Raspagem
A70: 59733020000114 | B70: AMFI CATÁLISE FUNDO DE INVESTIMENTO EM DIREITOS CREDITÓRIOS DE RESPONSABILIDADE LIMITADA | C70: Raspagem
... A74: 60485375000110 | B74: BTG DESENVOLVE SP FUNDO DE INVESTIMENTO EM DIREITOS CREDITÓRIOS | C74: Raspagem
A75: 60485375000110 | C75: Raspagem
A76: 61669748000176 | B76: LAVORO FORNECEDORES FUNDO DE INVESTIMENTO EM DIREITOS CREDITÓRIOS DO AGRONEGÓCIO - RESPONSABILIDADE LIMITADA | C76: Raspagem
A77: 63985990000184 | B77: BANDEIRANTES FUNDO DE INVESTIMENTO EM DIREITOS CREDITÓRIOS DO AGRONEGÓCIO DE RESPONSABILIDADE LIMITADA | C77: Raspagem
A78: 64096545000126 | B78: FEX AGRO FIDC RESPONSABILIDADE LIMITADA | C78: Raspagem
A79: 13895002000138 | B79: POLICARD II FUNDO DE INVESTIMENTO EM DIREITOS CREDITÓRIOS RESPONSABILIDADE LIMITADA | C79: Raspagem
A80: 19599487000107 | B80: FUNDO DE INVESTIMENTO EM DIREITOS CREDITÓRIOS ZIPDIN I | C80: Raspagem
A81: 23521077000102 | B81: CONSIGA MAIS FUNDO DE INVESTIMENTO EM DIREITOS CREDITÓRIOS | C81: Raspagem
A82: 24552987000115 | B82: NDMP I FUNDO DE INVESTIMENTO EM DIREITOS CREDITÓRIOS | C82: Raspagem
A83: 25248974000110 | B83: Fundo de Investimento em Direitos Creditórios Angá Sabemi Consignados | C83: Raspagem
A84: 27985097000195 | B84: ALIANÇA FUNDO DE INVESTIMENTO EM DIREITOS CREDITÓRIOS CONSIGNADOS | C84: Raspagem
A85: 29242913000104 | B85: Fundo de Investimento em Direitos Creditórios Neon FGTS | C85: Raspagem
A86: 30035329000159 | B86: VIA INVEST II FUNDO DE INVESTIMENTO EM DIREITOS CREDITÓRIOS | C86: Raspagem
A87: 30366120000178 | B87: Fundo de Investimento em Direitos Creditórios VCK Consignados | C87: Raspagem
... A91: 32724252000150 | B91: RB CAPITAL CREDIT ALPHA STRATEGY I FUNDO DE INVESTIMENTO EM DIREITOS CREDITÓRIOS – RESPONSABILIDADE LIMITADA | C91: Raspagem
A92: 32724252000150 | C92: Raspagem
A93: 33512746000133 | B93: FUNDO DE INVESTIMENTO EM DIREITOS CREDITÓRIOS BRZ CAPITAL CONSIG I RESPONSABILIDADE | C93: Raspagem
A94: 34218960000144 | B94: Fundo de Investimento em Direitos Creditórios Alion Consignados | C94: Raspagem
A95: 35946113000169 | B95: Fundo de Investimento em Direitos Creditórios Financeiros Facta Consignado INSS de Responsabilidade Limitada | C95: Raspagem
A96: 38082159000175 | B96: FACTA INSS CB FUNDO DE INVESTIMENTO EM DIREITOS CREDITÓRIOS - RESPONSABILIDADE LIMITADA | C96: Raspagem
A97: 38440284000100 | B97: CANAL 75 FUNDO DE INVESTIMENTO EM DIREITOS CREDITÓRIOS | C97: Raspagem
A98: 39663988000104 | B98: SPARK FUNDO DE INVESTIMENTO EM DIREITOS CREDITÓRIOS DE RESPONSABILIDADE LIMITADA | C98: Raspagem
A99: 40188893000165 | B99: BAVIERA FUNDO DE INVESTIMENTO EM DIREITOS CREDITÓRIOS - RESPONSABILIDADE LIMITADA | C99: Raspagem
A100: 40365950000134 | B100: INSS CONSIGNADO (PDL) I FUNDO DE INVESTIMENTO EM DIREITOS CREDITÓRIOS | C100: Raspagem
A101: 40365950000134 | B101: INSS CONSIGNADO (PDL) I FUNDO DE INVESTIMENTO EM DIREITOS CREDITÓRIOS RESPONSABILIDADE LIMITADA | C101: Raspagem
A102: 40752367000186 | B102: MT INSS RECEIVABLES II FUNDO DE INVESTIMENTO EM DIREITOS CREDITÓRIOS RESPONSABILIDADE LIMITADA | C102: Raspagem
A103: 40752367000186 | B103: MT INSS RECEIVABLES II FIDC | C103: Raspagem
A104: 41609394000167 | B104: VERSATILE FUNDO DE INVESTIMENTO EM DIREITOS CREDITÓRIOS | C104: Raspagem
... A111: 44642151000119 | B111: EMPRESTA I FUNDO DE INVESTIMENTO EM DIREITOS CREDITÓRIOS FINANCEIROS | C111: Raspagem
A112: 44642151000119 | C112: Raspagem
...
